openclimatedata/__init__.py
openclimatedata/_ceds.py
openclimatedata/_gcb_fossil.py
openclimatedata/_gcb_national.py
openclimatedata/_global_carbon_budget/__init__.py
openclimatedata/_global_carbon_budget/_core.py
openclimatedata/_global_carbon_budget/_gcb2021.py
openclimatedata/_global_carbon_budget/_gcb2022.py
openclimatedata/_global_carbon_budget/_gcb2023.py
openclimatedata/_primap_hist/__init__.py
openclimatedata/_primap_hist/_core.py
openclimatedata-0.23.dist-info/licenses/LICENSE
openclimatedata-0.23.dist-info/METADATA
openclimatedata-0.23.dist-info/WHEEL
openclimatedata-0.23.dist-info/top_level.txt
openclimatedata-0.23.dist-info/RECORD
